typegram/__init__.py
typegram/robot.py
typegram/api/__init__.py
typegram/api/all.py
typegram/api/object.py
typegram/api/utils.py
typegram/api/ayiin/__init__.py
typegram/api/ayiin/accountDaysTTL.py
typegram/api/ayiin/appWebViewResult.py
typegram/api/ayiin/attachMenuBot.py
typegram/api/ayiin/attachMenuBotIcon.py
typegram/api/ayiin/attachMenuBotIconColor.py
typegram/api/ayiin/attachMenuBots.py
typegram/api/ayiin/attachMenuBotsBot.py
typegram/api/ayiin/authorization.py
typegram/api/ayiin/autoDownloadSettings.py
typegram/api/ayiin/autoSaveException.py
typegram/api/ayiin/autoSaveSettings.py
typegram/api/ayiin/availableEffect.py
typegram/api/ayiin/availableReaction.py
typegram/api/ayiin/bankCardOpenUrl.py
typegram/api/ayiin/birthday.py
typegram/api/ayiin/boost.py
typegram/api/ayiin/botApp.py
typegram/api/ayiin/botBusinessConnection.py
typegram/api/ayiin/botCommand.py
typegram/api/ayiin/botCommandScope.py
typegram/api/ayiin/botInfo.py
typegram/api/ayiin/botInlineMessage.py
typegram/api/ayiin/botInlineResult.py
typegram/api/ayiin/botMenuButton.py
typegram/api/ayiin/broadcastRevenueBalances.py
typegram/api/ayiin/broadcastRevenueTransaction.py
typegram/api/ayiin/businessAwayMessage.py
typegram/api/ayiin/businessAwayMessageSchedule.py
typegram/api/ayiin/businessBotRecipients.py
typegram/api/ayiin/businessChatLink.py
typegram/api/ayiin/businessGreetingMessage.py
typegram/api/ayiin/businessIntro.py
typegram/api/ayiin/businessLocation.py
typegram/api/ayiin/businessRecipients.py
typegram/api/ayiin/businessWeeklyOpen.py
typegram/api/ayiin/businessWorkHours.py
typegram/api/ayiin/cdnConfig.py
typegram/api/ayiin/cdnPublicKey.py
typegram/api/ayiin/channelAdminLogEvent.py
typegram/api/ayiin/channelAdminLogEventAction.py
typegram/api/ayiin/channelAdminLogEventsFilter.py
typegram/api/ayiin/channelLocation.py
typegram/api/ayiin/channelMessagesFilter.py
typegram/api/ayiin/channelParticipant.py
typegram/api/ayiin/channelParticipantsFilter.py
typegram/api/ayiin/chat.py
typegram-0.0.2.dist-info/LICENSE
typegram-0.0.2.dist-info/METADATA
typegram-0.0.2.dist-info/WHEEL
typegram-0.0.2.dist-info/top_level.txt
typegram-0.0.2.dist-info/RECORD
