Metadata-Version: 2.1
Name: typegram
Version: 0.0.2
Summary: Telegram MTProto API framework in Python for bots.
Home-page: https://github.com/AyiinXd/typegram
Author: AyiinXd
Author-email: ayiincorporation@gmail.com
License: MIT
Project-URL: Bug Tracker, https://github.com/AyiinXd/typegram/issues
Project-URL: Source Code, https://github.com/AyiinXd/typegram
Keywords: telegram api chat bots library messaging mtproto
Classifier: Programming Language :: Python :: 3
Classifier: Programming Language :: Python :: 3.8
Classifier: Programming Language :: Python :: 3.9
Classifier: Programming Language :: Python :: 3.10
Classifier: Programming Language :: Python :: 3.11
Classifier: Programming Language :: Python :: 3.12
Classifier: Development Status :: 5 - Production/Stable
Classifier: Intended Audience :: Developers
Classifier: Topic :: Communications :: Chat
Classifier: License :: OSI Approved :: MIT License
Classifier: Operating System :: OS Independent
Requires-Python: ~=3.7
License-File: LICENSE
Requires-Dist: asyncio ==3.4.3
Requires-Dist: requests ==2.32.3
